[{"scenicName":"济南方特东方神画","scenicStatus":"上架","scenicType":"景区门票","scenicAddress":"山东省/济南市/槐荫区吴家堡济齐路227号（西客站北侧）","showMoreFlag":false,"scenicImages":"http://www.liuyiqinzi.com/uploads/20190924/2df40224a987c259b7c2e5df11bc8b9f.jpg","goodsList":[{"id":"1","name":"成人票（济南/莱芜不可用）","address":"济南市中心","type":"成人票","cPrice":"175.00","xPrice":"188.00","mPrice":"280.00","date":"2020-07-31 23:59:01","status":"正常","weidth":0}]},{"scenicName":"济南方特东方神画","scenicStatus":"上架","scenicType":"景区门票","scenicAddress":"山东省/济南市/槐荫区吴家堡济齐路227号（西客站北侧）","showMoreFlag":false,"scenicImages":"http://www.liuyiqinzi.com/uploads/20190925/892fb4abbe1bdda777198382205846bb.jpg","goodsList":[]},{"scenicName":"济南方特东方神画","scenicStatus":"上架","scenicType":"景区门票","scenicAddress":"山东省/济南市/槐荫区吴家堡济齐路227号（西客站北侧）","showMoreFlag":false,"scenicImages":"http://www.liuyiqinzi.com/uploads/20190925/93fcb52008996294317f1c66b83bf285.jpg","goodsList":[{"id":"1","name":"成人票（济南/莱芜不可用）","address":"济南市中心","type":"成人票","cPrice":"175.00","xPrice":"188.00","mPrice":"280.00","date":"2020-07-31 23:59:01","status":"正常","weidth":0},{"id":"11","name":"成人票（济南/莱芜不可用）","address":"济南市中心","type":"成人票","cPrice":"175.00","xPrice":"188.00","mPrice":"280.00","date":"2020-07-31 23:59:01","status":"正常","weidth":0},{"id":"11","name":"成人票（济南/莱芜不可用）","address":"济南市中心","type":"成人票","cPrice":"175.00","xPrice":"188.00","mPrice":"280.00","date":"2020-07-31 23:59:01","status":"正常","weidth":0},{"id":"11","name":"成人票（济南/莱芜不可用）","address":"济南市中心","type":"成人票","cPrice":"175.00","xPrice":"188.00","mPrice":"280.00","date":"2020-07-31 23:59:01","status":"正常","weidth":0},{"id":"11","name":"成人票（济南/莱芜不可用）","address":"济南市中心","type":"成人票","cPrice":"175.00","xPrice":"188.00","mPrice":"280.00","date":"2020-07-31 23:59:01","status":"正常","weidth":0},{"id":"11","name":"成人票（济南/莱芜不可用）","address":"济南市中心","type":"成人票","cPrice":"175.00","xPrice":"188.00","mPrice":"280.00","date":"2020-07-31 23:59:01","status":"正常","weidth":0},{"id":"11","name":"成人票（济南/莱芜不可用）","address":"济南市中心","type":"成人票","cPrice":"175.00","xPrice":"188.00","mPrice":"280.00","date":"2020-07-31 23:59:01","status":"正常","weidth":0},{"id":"11","name":"成人票（济南/莱芜不可用）","address":"济南市中心","type":"成人票","cPrice":"175.00","xPrice":"188.00","mPrice":"280.00","date":"2020-07-31 23:59:01","status":"正常","weidth":0}]}]